jsonpath_rust_py-0.3.3.dist-info/METADATA
jsonpath_rust_py-0.3.3.dist-info/WHEEL
jsonpath_rust_py-0.3.3.dist-info/license_files/LICENSE
jsonpath_rust_py/__init__.py
jsonpath_rust_py/jsonpath_rust_py.cpython-39-aarch64-linux-gnu.so
jsonpath_rust_py-0.3.3.dist-info/RECORD
